<annotation verified="yes">
    <folder>Annotation</folder>
    <filename>Car%20(10641).png</filename>
    <path>Car-PascalVOC-export/Annotations/Car%20(10641).png</path>
    <source>
        <database>Unknown</database>
    </source>
    <size>
        <width>100</width>
        <height>100</height>
        <depth>3</depth>
    </size>
    <segmented>0</segmented>
    <object>
    <name>Car</name>
    <pose>Unspecified</pose>
    <truncated>0</truncated>
    <difficult>0</difficult>
    <bndbox>
        <xmin>40.70175438596491</xmin>
        <ymin>42.63157894736842</ymin>
        <xmax>72.98245614035088</xmax>
        <ymax>74.91228070175438</ymax>
    </bndbox>
</object>
</annotation>
