<annotation verified="yes">
    <folder>Annotation</folder>
    <filename>Car%20(10450).png</filename>
    <path>Car-PascalVOC-export/Annotations/Car%20(10450).png</path>
    <source>
        <database>Unknown</database>
    </source>
    <size>
        <width>100</width>
        <height>100</height>
        <depth>3</depth>
    </size>
    <segmented>0</segmented>
    <object>
    <name>Car</name>
    <pose>Unspecified</pose>
    <truncated>0</truncated>
    <difficult>0</difficult>
    <bndbox>
        <xmin>1.048951048951049</xmin>
        <ymin>69.93006993006993</ymin>
        <xmax>16.433566433566433</xmax>
        <ymax>96.85314685314685</ymax>
    </bndbox>
</object>
</annotation>
