<annotation verified="yes">
    <folder>Annotation</folder>
    <filename>Car%20(10847).png</filename>
    <path>Car-PascalVOC-export/Annotations/Car%20(10847).png</path>
    <source>
        <database>Unknown</database>
    </source>
    <size>
        <width>100</width>
        <height>100</height>
        <depth>3</depth>
    </size>
    <segmented>0</segmented>
    <object>
    <name>Car</name>
    <pose>Unspecified</pose>
    <truncated>0</truncated>
    <difficult>0</difficult>
    <bndbox>
        <xmin>17.543859649122805</xmin>
        <ymin>38.421052631578945</ymin>
        <xmax>89.12280701754386</xmax>
        <ymax>100</ymax>
    </bndbox>
</object>
</annotation>
