<annotation verified="yes">
    <folder>Annotation</folder>
    <filename>1%20(2038).png</filename>
    <path>Bridge-PascalVOC-export/Annotations/1%20(2038).png</path>
    <source>
        <database>Unknown</database>
    </source>
    <size>
        <width>100</width>
        <height>100</height>
        <depth>3</depth>
    </size>
    <segmented>0</segmented>
    <object>
    <name>Bridge</name>
    <pose>Unspecified</pose>
    <truncated>0</truncated>
    <difficult>0</difficult>
    <bndbox>
        <xmin>6.691449814126393</xmin>
        <ymin>26.208178438661708</ymin>
        <xmax>93.3085501858736</xmax>
        <ymax>66.72862453531599</ymax>
    </bndbox>
</object>
</annotation>
