<annotation verified="yes">
    <folder>Annotation</folder>
    <filename>1%20(1529).png</filename>
    <path>Bridge-PascalVOC-export/Annotations/1%20(1529).png</path>
    <source>
        <database>Unknown</database>
    </source>
    <size>
        <width>100</width>
        <height>100</height>
        <depth>3</depth>
    </size>
    <segmented>0</segmented>
    <object>
    <name>Bridge</name>
    <pose>Unspecified</pose>
    <truncated>0</truncated>
    <difficult>0</difficult>
    <bndbox>
        <xmin>3.3457249070631967</xmin>
        <ymin>3.531598513011152</ymin>
        <xmax>92.93680297397769</xmax>
        <ymax>44.05204460966543</ymax>
    </bndbox>
</object>
</annotation>
