<annotation verified="yes">
    <folder>Annotation</folder>
    <filename>Bus%20(1043).png</filename>
    <path>Bus-PascalVOC-export/Annotations/Bus%20(1043).png</path>
    <source>
        <database>Unknown</database>
    </source>
    <size>
        <width>100</width>
        <height>100</height>
        <depth>3</depth>
    </size>
    <segmented>0</segmented>
    <object>
    <name>Bus</name>
    <pose>Unspecified</pose>
    <truncated>0</truncated>
    <difficult>0</difficult>
    <bndbox>
        <xmin>30.419580419580416</xmin>
        <ymin>36.71328671328671</ymin>
        <xmax>94.05594405594405</xmax>
        <ymax>90.55944055944056</ymax>
    </bndbox>
</object>
</annotation>
