<annotation verified="yes">
    <folder>Annotation</folder>
    <filename>a%20(10309).png</filename>
    <path>Boat-PascalVOC-export/Annotations/a%20(10309).png</path>
    <source>
        <database>Unknown</database>
    </source>
    <size>
        <width>100</width>
        <height>100</height>
        <depth>3</depth>
    </size>
    <segmented>0</segmented>
    <object>
    <name>Boat</name>
    <pose>Unspecified</pose>
    <truncated>0</truncated>
    <difficult>0</difficult>
    <bndbox>
        <xmin>1.8587360594795537</xmin>
        <ymin>23.605947955390334</ymin>
        <xmax>91.07806691449814</xmax>
        <ymax>87.54646840148698</ymax>
    </bndbox>
</object>
</annotation>
