<annotation verified="yes">
    <folder>Annotation</folder>
    <filename>a%20(10778).png</filename>
    <path>Boat-PascalVOC-export/Annotations/a%20(10778).png</path>
    <source>
        <database>Unknown</database>
    </source>
    <size>
        <width>100</width>
        <height>100</height>
        <depth>3</depth>
    </size>
    <segmented>0</segmented>
    <object>
    <name>Boat</name>
    <pose>Unspecified</pose>
    <truncated>0</truncated>
    <difficult>0</difficult>
    <bndbox>
        <xmin>8.921933085501859</xmin>
        <ymin>36.2453531598513</ymin>
        <xmax>100</xmax>
        <ymax>96.46840148698884</ymax>
    </bndbox>
</object>
</annotation>
