<annotation verified="yes">
    <folder>Annotation</folder>
    <filename>a%20(10885).png</filename>
    <path>Boat-PascalVOC-export/Annotations/a%20(10885).png</path>
    <source>
        <database>Unknown</database>
    </source>
    <size>
        <width>100</width>
        <height>100</height>
        <depth>3</depth>
    </size>
    <segmented>0</segmented>
    <object>
    <name>Boat</name>
    <pose>Unspecified</pose>
    <truncated>0</truncated>
    <difficult>0</difficult>
    <bndbox>
        <xmin>24.90706319702602</xmin>
        <ymin>36.617100371747206</ymin>
        <xmax>72.8624535315985</xmax>
        <ymax>61.524163568773226</ymax>
    </bndbox>
</object>
</annotation>
