<annotation verified="yes">
    <folder>Annotation</folder>
    <filename>a%20(10348).png</filename>
    <path>Boat-PascalVOC-export/Annotations/a%20(10348).png</path>
    <source>
        <database>Unknown</database>
    </source>
    <size>
        <width>100</width>
        <height>100</height>
        <depth>3</depth>
    </size>
    <segmented>0</segmented>
    <object>
    <name>Boat</name>
    <pose>Unspecified</pose>
    <truncated>0</truncated>
    <difficult>0</difficult>
    <bndbox>
        <xmin>20.07434944237918</xmin>
        <ymin>44.795539033457246</ymin>
        <xmax>98.14126394052045</xmax>
        <ymax>86.05947955390334</ymax>
    </bndbox>
</object>
</annotation>
