<annotation verified="yes">
    <folder>Annotation</folder>
    <filename>1%20(1450).png</filename>
    <path>Palm-tree-PascalVOC-export/Annotations/1%20(1450).png</path>
    <source>
        <database>Unknown</database>
    </source>
    <size>
        <width>100</width>
        <height>100</height>
        <depth>3</depth>
    </size>
    <segmented>0</segmented>
    <object>
    <name>Palm tree</name>
    <pose>Unspecified</pose>
    <truncated>0</truncated>
    <difficult>0</difficult>
    <bndbox>
        <xmin>17.014925373134325</xmin>
        <ymin>3.432835820895522</ymin>
        <xmax>57.014925373134325</xmax>
        <ymax>75.07462686567163</ymax>
    </bndbox>
</object>
</annotation>
