<annotation verified="yes">
    <folder>Annotation</folder>
    <filename>032a02a743a34e528dfcd6d392b44bfe.png</filename>
    <path>Statue-PascalVOC-export/Annotations/032a02a743a34e528dfcd6d392b44bfe.png</path>
    <source>
        <database>Unknown</database>
    </source>
    <size>
        <width>100</width>
        <height>100</height>
        <depth>3</depth>
    </size>
    <segmented>0</segmented>
    <object>
    <name>Statue</name>
    <pose>Unspecified</pose>
    <truncated>0</truncated>
    <difficult>0</difficult>
    <bndbox>
        <xmin>26.627218934911244</xmin>
        <ymin>5.621301775147929</ymin>
        <xmax>88.46153846153847</xmax>
        <ymax>96.44970414201184</ymax>
    </bndbox>
</object>
</annotation>
