<annotation verified="yes">
    <folder>Annotation</folder>
    <filename>06d227bc29c5490da549c47ad2c4a227.png</filename>
    <path>Statue-PascalVOC-export/Annotations/06d227bc29c5490da549c47ad2c4a227.png</path>
    <source>
        <database>Unknown</database>
    </source>
    <size>
        <width>100</width>
        <height>100</height>
        <depth>3</depth>
    </size>
    <segmented>0</segmented>
    <object>
    <name>Statue</name>
    <pose>Unspecified</pose>
    <truncated>0</truncated>
    <difficult>0</difficult>
    <bndbox>
        <xmin>28.698224852071007</xmin>
        <ymin>30.17751479289941</ymin>
        <xmax>55.32544378698225</xmax>
        <ymax>68.93491124260356</ymax>
    </bndbox>
</object>
</annotation>
