<annotation verified="yes">
    <folder>Annotation</folder>
    <filename>08437da8d05045ddadea0a4347b1bf1e.png</filename>
    <path>Statue-PascalVOC-export/Annotations/08437da8d05045ddadea0a4347b1bf1e.png</path>
    <source>
        <database>Unknown</database>
    </source>
    <size>
        <width>100</width>
        <height>100</height>
        <depth>3</depth>
    </size>
    <segmented>0</segmented>
    <object>
    <name>Statue</name>
    <pose>Unspecified</pose>
    <truncated>0</truncated>
    <difficult>0</difficult>
    <bndbox>
        <xmin>31.065088757396452</xmin>
        <ymin>31.952662721893493</ymin>
        <xmax>94.67455621301775</xmax>
        <ymax>90.53254437869823</ymax>
    </bndbox>
</object>
</annotation>
