<annotation verified="yes">
    <folder>Annotation</folder>
    <filename>0dcaa897bd7f4b68bde8eb2754bafe86.png</filename>
    <path>Statue-PascalVOC-export/Annotations/0dcaa897bd7f4b68bde8eb2754bafe86.png</path>
    <source>
        <database>Unknown</database>
    </source>
    <size>
        <width>100</width>
        <height>100</height>
        <depth>3</depth>
    </size>
    <segmented>0</segmented>
    <object>
    <name>Statue</name>
    <pose>Unspecified</pose>
    <truncated>0</truncated>
    <difficult>0</difficult>
    <bndbox>
        <xmin>5.325443786982249</xmin>
        <ymin>5.029585798816568</ymin>
        <xmax>82.24852071005917</xmax>
        <ymax>74.55621301775149</ymax>
    </bndbox>
</object>
</annotation>
