<annotation verified="yes">
    <folder>Annotation</folder>
    <filename>TL%20(10514).png</filename>
    <path>Traffic-light-PascalVOC-export/Annotations/TL%20(10514).png</path>
    <source>
        <database>Unknown</database>
    </source>
    <size>
        <width>100</width>
        <height>100</height>
        <depth>3</depth>
    </size>
    <segmented>0</segmented>
    <object>
    <name>Traffic light</name>
    <pose>Unspecified</pose>
    <truncated>0</truncated>
    <difficult>0</difficult>
    <bndbox>
        <xmin>30.76923076923077</xmin>
        <ymin>3.550295857988166</ymin>
        <xmax>71.00591715976331</xmax>
        <ymax>85.20710059171597</ymax>
    </bndbox>
</object>
</annotation>
