<annotation verified="yes">
    <folder>Annotation</folder>
    <filename>TL%20(10134).png</filename>
    <path>Traffic-light-PascalVOC-export/Annotations/TL%20(10134).png</path>
    <source>
        <database>Unknown</database>
    </source>
    <size>
        <width>100</width>
        <height>100</height>
        <depth>3</depth>
    </size>
    <segmented>0</segmented>
    <object>
    <name>Traffic light</name>
    <pose>Unspecified</pose>
    <truncated>0</truncated>
    <difficult>0</difficult>
    <bndbox>
        <xmin>11.834319526627219</xmin>
        <ymin>28.40236686390533</ymin>
        <xmax>82.54437869822485</xmax>
        <ymax>53.550295857988175</ymax>
    </bndbox>
</object>
</annotation>
