<annotation verified="yes">
    <folder>Annotation</folder>
    <filename>TL%20(10847).png</filename>
    <path>Traffic-light-PascalVOC-export/Annotations/TL%20(10847).png</path>
    <source>
        <database>Unknown</database>
    </source>
    <size>
        <width>100</width>
        <height>100</height>
        <depth>3</depth>
    </size>
    <segmented>0</segmented>
    <object>
    <name>Traffic light</name>
    <pose>Unspecified</pose>
    <truncated>0</truncated>
    <difficult>0</difficult>
    <bndbox>
        <xmin>3.8461538461538463</xmin>
        <ymin>0</ymin>
        <xmax>47.0414201183432</xmax>
        <ymax>65.08875739644971</ymax>
    </bndbox>
</object>
</annotation>
