<annotation verified="yes">
    <folder>Annotation</folder>
    <filename>c%20(11011).png</filename>
    <path>Chimney-PascalVOC-export/Annotations/c%20(11011).png</path>
    <source>
        <database>Unknown</database>
    </source>
    <size>
        <width>100</width>
        <height>100</height>
        <depth>3</depth>
    </size>
    <segmented>0</segmented>
    <object>
    <name>Chimney</name>
    <pose>Unspecified</pose>
    <truncated>0</truncated>
    <difficult>0</difficult>
    <bndbox>
        <xmin>34.61538461538461</xmin>
        <ymin>13.636363636363635</ymin>
        <xmax>58.391608391608386</xmax>
        <ymax>54.54545454545454</ymax>
    </bndbox>
</object>
</annotation>
