<annotation verified="yes">
    <folder>Annotation</folder>
    <filename>088512c8d706478da8bbec1a9297281d.png</filename>
    <path>Tree-PascalVOC-export/Annotations/088512c8d706478da8bbec1a9297281d.png</path>
    <source>
        <database>Unknown</database>
    </source>
    <size>
        <width>100</width>
        <height>100</height>
        <depth>3</depth>
    </size>
    <segmented>0</segmented>
    <object>
    <name>Tree</name>
    <pose>Unspecified</pose>
    <truncated>0</truncated>
    <difficult>0</difficult>
    <bndbox>
        <xmin>30.17751479289941</xmin>
        <ymin>4.733727810650888</ymin>
        <xmax>100</xmax>
        <ymax>100</ymax>
    </bndbox>
</object>
</annotation>
