<annotation verified="yes">
    <folder>Annotation</folder>
    <filename>09a29e13091a4d2c88d274bca89e9333.png</filename>
    <path>Tree-PascalVOC-export/Annotations/09a29e13091a4d2c88d274bca89e9333.png</path>
    <source>
        <database>Unknown</database>
    </source>
    <size>
        <width>100</width>
        <height>100</height>
        <depth>3</depth>
    </size>
    <segmented>0</segmented>
    <object>
    <name>Tree</name>
    <pose>Unspecified</pose>
    <truncated>0</truncated>
    <difficult>0</difficult>
    <bndbox>
        <xmin>1.775147928994083</xmin>
        <ymin>18.639053254437872</ymin>
        <xmax>10.059171597633135</xmax>
        <ymax>44.082840236686394</ymax>
    </bndbox>
</object>
</annotation>
