<annotation verified="yes">
    <folder>Annotation</folder>
    <filename>0b20ad21f68a440e87de6ab8ead891be.png</filename>
    <path>Tree-PascalVOC-export/Annotations/0b20ad21f68a440e87de6ab8ead891be.png</path>
    <source>
        <database>Unknown</database>
    </source>
    <size>
        <width>100</width>
        <height>100</height>
        <depth>3</depth>
    </size>
    <segmented>0</segmented>
    <object>
    <name>Tree</name>
    <pose>Unspecified</pose>
    <truncated>0</truncated>
    <difficult>0</difficult>
    <bndbox>
        <xmin>5.9171597633136095</xmin>
        <ymin>8.875739644970414</ymin>
        <xmax>56.2130177514793</xmax>
        <ymax>52.95857988165681</ymax>
    </bndbox>
</object>
</annotation>
