<annotation verified="yes">
    <folder>Annotation</folder>
    <filename>0d77025619f2462fbdcefb8f02cbf4a8.png</filename>
    <path>Tree-PascalVOC-export/Annotations/0d77025619f2462fbdcefb8f02cbf4a8.png</path>
    <source>
        <database>Unknown</database>
    </source>
    <size>
        <width>100</width>
        <height>100</height>
        <depth>3</depth>
    </size>
    <segmented>0</segmented>
    <object>
    <name>Tree</name>
    <pose>Unspecified</pose>
    <truncated>0</truncated>
    <difficult>0</difficult>
    <bndbox>
        <xmin>11.834319526627219</xmin>
        <ymin>0</ymin>
        <xmax>100</xmax>
        <ymax>44.37869822485207</ymax>
    </bndbox>
</object>
</annotation>
