<annotation verified="yes">
    <folder>Annotation</folder>
    <filename>MT1%20(10263).png</filename>
    <path>Motorcycle-PascalVOC-export/Annotations/MT1%20(10263).png</path>
    <source>
        <database>Unknown</database>
    </source>
    <size>
        <width>100</width>
        <height>100</height>
        <depth>3</depth>
    </size>
    <segmented>0</segmented>
    <object>
    <name>Motorcycle</name>
    <pose>Unspecified</pose>
    <truncated>0</truncated>
    <difficult>0</difficult>
    <bndbox>
        <xmin>31.952662721893493</xmin>
        <ymin>30.47337278106509</ymin>
        <xmax>52.9585798816568</xmax>
        <ymax>60.94674556213018</ymax>
    </bndbox>
</object>
</annotation>
